visual_sort/__init__.py
visual_sort/visualsort.py
visualsort_kubii10-0.1.0.dist-info/METADATA
visualsort_kubii10-0.1.0.dist-info/WHEEL
visualsort_kubii10-0.1.0.dist-info/top_level.txt
visualsort_kubii10-0.1.0.dist-info/RECORD
