Metadata-Version: 2.4
Name: visualsort-kubii10
Version: 0.1.0
Summary: Library to visualise sorting
Author-email: Kubii10 <supcod34@email.com>
Requires-Python: >=3.8
Requires-Dist: pygame>=2.0.0
